<?xml version="1.0" encoding="utf-8"?>
<Catalog>
    <CModel id="ArbiterSCBWCastModel" parent="OneShotSpellFX">
        <Model value="Assets\Effects\Protoss\Arbiter_StasisField_Shockwave\Arbiter_StasisField_Shockwave.m3"/>
        <EditorCategories value="Race:Protoss"/>
        <Radius value="5.000000"/>
        <RadiusLoose value="5.000000"/>
    </CModel>
    <CModel id="ArbiterSCBWStasisFieldImpact" parent="RaceImpactFX" Race="Protoss">
        <Model value="Assets\Effects\Protoss\Arbiter_StasisField_Impact\Arbiter_StasisField_Impact.m3"/>
    </CModel>
    <CModel id="ArbiterSCBWRecalledImpact" parent="OneShotSpellFX">
        <Model value="Assets\Effects\Protoss\RecallImpactIn\RecallImpactIn.m3"/>
        <EditorCategories value="Race:Protoss"/>
        <ScaleMax value="0.750000,0.750000,0.750000"/>
        <ScaleMin value="0.750000,0.750000,0.750000"/>
    </CModel>
    <CModel id="ArbiterSCBWRecallingImpact" parent="OneShotSpellFX">
        <Model value="Assets\Effects\Protoss\RecallImpactOut\RecallImpactOut.m3"/>
        <EditorCategories value="Race:Protoss"/>
        <ScaleMax value="0.750000,0.750000,0.750000"/>
        <ScaleMin value="0.750000,0.750000,0.750000"/>
    </CModel>
    <CModel id="ArbiterSCBWRecallSearchStart" parent="OneShotSpellFX">
        <Model value="Assets\Effects\Protoss\SingularityAreaImpact\SingularityAreaImpact.m3"/>
        <EditorCategories value="Race:Protoss"/>
    </CModel>
    <CModel id="ArbiterSCBWWeaponImpact" parent="ImpactFX">
        <Model value="Assets\Effects\Protoss\PhotonCannonMissileImpact\PhotonCannonMissileImpact.m3"/>
        <EditorCategories value="Race:Protoss"/>
    </CModel>
    <CModel id="ArbiterSCBWWeaponMissile" parent="MissileFX">
        <Model value="Assets\Effects\Protoss\PhotonMissile\PhotonMissile.m3"/>
        <EditorCategories value="Race:Protoss"/>
        <ScaleMax value="1.500000,1.500000,1.500000"/>
        <ScaleMin value="1.500000,1.500000,1.500000"/>
    </CModel>
    <CModel id="ArchonSCBWAttackBeam" parent="PersistentSpellFX">
        <Model value="Assets\Effects\Protoss\ArchonBeam\ArchonBeam.m3"/>
        <LowQualityModel value="ArchonAttackBeamLow"/>
        <EditorCategories value="Race:Protoss"/>
        <RadiusLoose value="1.000000"/>
    </CModel>
    <CModel id="DarkArchonSCBWMindControlImpact" parent="PersistentSpellFX">
        <Model value="Assets\Effects\Protoss\Zealot_Nerazim_PhaseChargeStun_Impact\Zealot_Nerazim_PhaseChargeStun_Impact.m3"/>
        <EditorCategories value="Race:Protoss"/>
        <Lighting value="DarkArchonSCBWMaelstromStunImpact"/>
    </CModel>
    <CModel id="DarkArchonSCBWMindControlBeam" parent="PersistentSpellFX">
        <Model value="Assets\Effects\Protoss\DarkArchon_MindControl_Beam\DarkArchon_MindControl_Beam.m3"/>
        <EditorCategories value="Race:Protoss"/>
    </CModel>
    <CModel id="DarkArchonSCBWMindControlState" parent="PersistentSpellFX">
        <Model value="Assets\Effects\Protoss\DarkArchon_MindControl_State\DarkArchon_MindControl_State.m3"/>
        <EditorCategories value="Race:Protoss"/>
    </CModel>
    <CModel id="DarkArchonSCBWMaelstromImpact" parent="OneShotSpellFX">
        <Model value="Assets\Effects\Terran\MindBlastImpact\MindBlastImpact.m3"/>
        <EditorCategories value="Race:Protoss"/>
    </CModel>
    <CModel id="DarkArchonSCBWMaelstromStunImpact" parent="PersistentSpellFX">
        <Model value="Assets\Effects\Protoss\Maelstrom\Maelstrom.m3"/>
        <EditorCategories value="Race:Protoss"/>
    </CModel>
    <CModel id="DragoonSCBWAttackImpact" parent="ImpactFX">
        <Model value="Assets\Effects\Protoss\DragoonEX2_Missile_Impact\DragoonEX2_Missile_Impact.m3"/>
        <EditorCategories value="Race:Protoss"/>
    </CModel>
    <CModel id="DragoonSCBWWeapon" parent="MissileFX">
        <Model value="Assets\Effects\Protoss\DragoonEX2_Missile\DragoonEX2_Missile.m3"/>
        <EditorCategories value="Race:Protoss"/>
    </CModel>
    <CModel id="DarkArchonSCBWFeedbackImpact" parent="PersistentSpellFX">
        <Model value="Assets\Effects\Protoss\FeedbackImpact\FeedbackImpact.m3"/>
        <EditorCategories value="Race:Protoss"/>
    </CModel>
    <CModel id="DarkArchonSCBWFeedbackLaunch" parent="OneShotSpellFX">
        <Model value="Assets\Effects\Protoss\FeedbackLaunch\FeedbackLaunch.m3"/>
        <EditorCategories value="Race:Protoss"/>
        <ScaleMax value="0.650000,0.650000,0.650000"/>
        <ScaleMin value="0.650000,0.650000,0.650000"/>
    </CModel>
    <CModel id="HighTemplarSCBWHallucinationBirth" parent="OneShotSpellFX">
        <Model value="Assets\Effects\Protoss\HallucinateBirth\HallucinateBirth.m3"/>
        <EditorCategories value="Race:Protoss"/>
    </CModel>
    <CModel id="HighTemplarSCBWPsiStormImpact" parent="ImpactFX">
        <Model value="Assets\Effects\Protoss\PsiStormImpact\PsiStormImpact.m3"/>
        <EditorCategories value="Race:Protoss"/>
        <Radius value="1.000000"/>
    </CModel>
    <CModel id="HighTemplarSCBWPsiStormModel" parent="PersistentSpellFX">
        <Model value="Assets\Effects\Protoss\PsiStorm\PsiStorm.m3"/>
        <EditorCategories value="Race:Protoss"/>
        <RadiusLoose value="1.000000"/>
    </CModel>
    <CModel id="InterceptorSCBWAttackBeam" parent="PersistentSpellFX">
        <Model value="Assets\Effects\Protoss\InterceptorMissile\InterceptorMissile.m3"/>
        <EditorCategories value="Race:Protoss"/>
    </CModel>
    <CModel id="InterceptorSCBWAttackImpact" parent="ImpactFX">
        <Model value="Assets\Effects\Protoss\InterceptorMissileImpact\InterceptorMissileImpact.m3"/>
        <EditorCategories value="Race:Protoss"/>
    </CModel>
    <CModel id="PhotonCannonSCBW" parent="Building" Race="Protoss">
        <Model value="Assets\Buildings\Protoss\PhotonCannonEx2\PhotonCannonEx2.m3"/>
        <AttachProps Id="Ref_TurretZ">
            <Keys index="Turret" value="0"/>
        </AttachProps>
        <Lighting value="PhotonCannon"/>
        <PlanetPanelCamera value="Star2CameraMid06"/>
        <Radius value="1.000000"/>
        <ScaleMax value="0.850000,0.850000,0.850000"/>
        <ScaleMin value="0.850000,0.850000,0.850000"/>
        <SelectionLayer value="2"/>
        <SelectionRadius value="1.176200"/>
        <ShadowRadius value="1.176200"/>
        <SquibTypeDefault value="Metal"/>
        <TechPurchaseCamera value="Star2CameraMid06"/>
        <TextureDeclares Prefix="photoncannon_">
            <Adaptions TriggerOnSubstring="_Diffuse" Slot="main"/>
            <Adaptions TriggerOnSubstring="_Specular" Slot="main"/>
            <Adaptions TriggerOnSubstring="_Emissive" Slot="main"/>
        </TextureDeclares>
        <TextureDeclares Prefix="photoncannonbase_">
            <Adaptions TriggerOnSubstring="_Diffuse" Slot="generic05"/>
            <Adaptions TriggerOnSubstring="_Specular" Slot="generic05"/>
            <Adaptions TriggerOnSubstring="_Emissive" Slot="generic05"/>
        </TextureDeclares>
        <TextureDeclares Prefix="lazerbolt1_">
            <Adaptions Slot="generic01"/>
        </TextureDeclares>
        <TextureDeclares Prefix="grad_">
            <Adaptions Slot="generic02"/>
        </TextureDeclares>
        <TextureDeclares Prefix="warpline2_">
            <Adaptions Slot="generic03"/>
        </TextureDeclares>
        <TextureDeclares Prefix="tronsquare1_">
            <Adaptions Slot="generic04"/>
        </TextureDeclares>
        <UnitGlossaryCamera value="Star2CameraMid06"/>
    </CModel>
    <CModel id="PhotonCannonSCBWAttackImpact" parent="ImpactFX">
        <Model value="Assets\Effects\Protoss\PhaseCannonMissileImpact\PhaseCannonMissileImpact.m3"/>
        <EditorCategories value="Race:Protoss"/>
    </CModel>
    <CModel id="PhotonCannonSCBWBirth" parent="PhotonCannonSCBW">
        <Model value="Assets\Buildings\Protoss\PhotonCannonWarpIn\PhotonCannonWarpIn.m3"/>
        <AttachProps index="0" removed="1"/>
        <Events>
            <Anim value="Stand,Build,End"/>
            <Name value="BuildingWarpIn"/>
            <Type value="Sound"/>
            <Time value="1.166600"/>
        </Events>
        <TextureDeclares index="2" removed="1"/>
        <TextureDeclares index="3" removed="1"/>
        <TextureDeclares index="4" removed="1"/>
        <TextureDeclares index="5" removed="1"/>
    </CModel>
    <CModel id="PhotonCannonSCBWDeath" parent="UnitDeath">
        <Model value="Assets\Buildings\Protoss\PhotonCannonDeathEx2\PhotonCannonDeathEx2_01.m3"/>
        <LowQualityModel value="ProtossSmallBuildingDeathLow"/>
        <EditorCategories value="Race:Protoss"/>
        <Lighting value="PhotonCannonDeath"/>
        <TextureDeclares Prefix="photoncannon_">
            <Adaptions TriggerOnSubstring="_Diffuse" Slot="main"/>
            <Adaptions TriggerOnSubstring="_Specular" Slot="main"/>
        </TextureDeclares>
        <TextureDeclares Prefix="photoncannonbase_">
            <Adaptions TriggerOnSubstring="_Diffuse" Slot="generic05"/>
            <Adaptions TriggerOnSubstring="_Specular" Slot="generic05"/>
        </TextureDeclares>
    </CModel>
    <CModel id="PhotonCannonSCBWDeathUnpowered" parent="UnitDeath">
        <Model value="Assets\Buildings\Protoss\PhotonCannonDeathUnpoweredEx1\PhotonCannonDeathUnpoweredEx1.m3"/>
        <LowQualityModel value="ProtossSmallBuildingDeathLow"/>
        <EditorCategories value="Race:Protoss"/>
        <Lighting value="PhotonCannonDeathUnpowered"/>
        <TextureDeclares Prefix="photoncannon_">
            <Adaptions TriggerOnSubstring="_Diffuse" Slot="main"/>
            <Adaptions TriggerOnSubstring="_Specular" Slot="main"/>
        </TextureDeclares>
        <TextureDeclares Prefix="photoncannonbase_">
            <Adaptions TriggerOnSubstring="_Diffuse" Slot="generic05"/>
            <Adaptions TriggerOnSubstring="_Specular" Slot="generic05"/>
        </TextureDeclares>
    </CModel>
    <CModel id="PhotonCannonSCBWPlacement" parent="Placement" Race="Protoss">
        <Model value="Assets\Buildings\Protoss\PhotonCannonPlacement\PhotonCannonPlacement.m3"/>
        <LowQualityModel value="PhotonCannon"/>
        <Lighting value="PhaseCannon"/>
        <Radius value="-1.000000"/>
        <ScaleMax value="0.850000,0.850000,0.850000"/>
        <ScaleMin value="0.850000,0.850000,0.850000"/>
        <SelectionRadius value="0.000000"/>
        <ShadowRadius value="0.000000"/>
    </CModel>
    <CModel id="PhotonCannonSCBWSplat" parent="Splat">
        <Model value="Assets\Splats\Splat_PhotonCannon\Splat_PhotonCannon.m3"/>
        <EditorCategories value="Race:Protoss"/>
        <ScaleMax value="0.850000,0.850000,0.850000"/>
        <ScaleMin value="0.850000,0.850000,0.850000"/>
    </CModel>
    <CModel id="PhotonCannonSCBWWeapon" parent="MissileFX">
        <Model value="Assets\Effects\Protoss\PhaseCannonMissile\PhaseCannonMissile.m3"/>
        <EditorCategories value="Race:Protoss"/>
    </CModel>
    <CModel id="ProbeSCBWAttackBeam" parent="PersistentSpellFX">
        <Model value="Assets\Effects\Protoss\ProbeBeam\ProbeBeam.m3"/>
        <EditorCategories value="Race:Protoss"/>
    </CModel>
    <CModel id="ProbeSCBWAttackImpact" parent="ImpactFX">
        <Model value="Assets\Effects\Protoss\ProbeImpact\ProbeImpact.m3"/>
        <EditorCategories value="Race:Protoss"/>
    </CModel>
    <CModel id="ProtossBuildingBirthSCBWLow" parent="Building" Race="Protoss">
        <Model value="Assets\Buildings\Protoss\ProtossBuild\ProtossBuild_Low.m3"/>
        <Radius value="1.000000"/>
        <SelectionLayer value="2"/>
        <SelectionRadius value="1.000000"/>
        <ShadowRadius value="1.000000"/>
    </CModel>
    <CModel id="ProtossBuildingBirthSCBWSmall" parent="Building" Race="Protoss">
        <Model value="Assets\Buildings\Protoss\ProtossBuild\ProtossBuild.m3"/>
        <LowQualityModel value="ProtossBuildingBirthSCBWLowSmall"/>
        <Radius value="1.000000"/>
        <ScaleMax value="0.800000,0.800000,0.800000"/>
        <ScaleMin value="0.800000,0.800000,0.800000"/>
        <SelectionLayer value="2"/>
        <SelectionRadius value="1.250000"/>
        <ShadowRadius value="1.250000"/>
    </CModel>
    <CModel id="ProtossBuildingBirthSCBWLowLarge" parent="Building" Race="Protoss">
        <Model value="Assets\Buildings\Protoss\ProtossBuild\ProtossBuild_Low.m3"/>
        <Radius value="1.000000"/>
        <ScaleMax value="1.200000,1.200000,1.200000"/>
        <ScaleMin value="1.200000,1.200000,1.200000"/>
        <SelectionLayer value="2"/>
        <SelectionRadius value="0.833200"/>
        <ShadowRadius value="0.833200"/>
    </CModel>
    <CModel id="ProtossBuildingBirthSCBWLowSmall" parent="Building" Race="Protoss">
        <Model value="Assets\Buildings\Protoss\ProtossBuild\ProtossBuild_Low.m3"/>
        <Radius value="1.000000"/>
        <ScaleMax value="0.800000,0.800000,0.800000"/>
        <ScaleMin value="0.800000,0.800000,0.800000"/>
        <SelectionLayer value="2"/>
        <SelectionRadius value="1.250000"/>
        <ShadowRadius value="1.250000"/>
    </CModel>
    <CModel id="ProtossBuildingBirthSCBWLarge" parent="Building" Race="Protoss">
        <Model value="Assets\Buildings\Protoss\ProtossBuild\ProtossBuild.m3"/>
        <LowQualityModel value="ProtossBuildingBirthSCBWLowLarge"/>
        <Radius value="1.000000"/>
        <ScaleMax value="1.200000,1.200000,1.200000"/>
        <ScaleMin value="1.200000,1.200000,1.200000"/>
        <SelectionLayer value="2"/>
        <SelectionRadius value="0.833200"/>
        <ShadowRadius value="0.833200"/>
    </CModel>
    <CModel id="ProtossBuildingBirthSCBW" parent="Building" Race="Protoss">
        <Model value="Assets\Buildings\Protoss\ProtossBuild\ProtossBuild.m3"/>
        <LowQualityModel value="ProtossBuildingBirthSCBWLow"/>
        <Radius value="1.000000"/>
        <SelectionLayer value="2"/>
        <SelectionRadius value="1.000000"/>
        <ShadowRadius value="1.000000"/>
    </CModel>
    <CModel id="AdvisorSCBWPortrait" parent="Portrait" Race="Protoss">
        <Model value="Assets\Portraits\Protoss\TalDarimExecutorPortrait\TalDarimExecutorPortrait.m3"/>
        <Image value="Assets\Textures\TalDarimExecutorPortrait_Static.dds"/>
    </CModel>
    <CModel id="CitadelOfAdunSCBW" parent="Building" Race="Protoss">
        <Model value="Assets\Buildings\Protoss\TwilightCouncilEx1\TwilightCouncilEx1.m3"/>
        <Lighting value="TwilightCouncil"/>
        <Radius value="1.500000"/>
        <ScaleMax value="0.750000,0.750000,0.750000"/>
        <ScaleMin value="0.750000,0.750000,0.750000"/>
        <SelectionLayer value="2"/>
        <SelectionRadius value="1.999700"/>
        <ShadowRadius value="1.999700"/>
        <SquibTypeDefault value="Metal"/>
        <TextureDeclares Prefix="twilightcouncil_">
            <Adaptions TriggerOnSubstring="_Diffuse" Slot="main"/>
            <Adaptions TriggerOnSubstring="_Specular" Slot="main"/>
            <Adaptions TriggerOnSubstring="_Emissive" Slot="main"/>
        </TextureDeclares>
        <TextureDeclares Prefix="grad_">
            <Adaptions Slot="generic02"/>
        </TextureDeclares>
        <TextureDeclares Prefix="pulse1_">
            <Adaptions Slot="generic03"/>
        </TextureDeclares>
    </CModel>
    <CModel id="CitadelOfAdunSCBWBirth" parent="CitadelOfAdunSCBW">
        <Model value="Assets\Buildings\Protoss\TwilightCouncilWarpIn\TwilightCouncilWarpIn.m3"/>
        <Events>
            <Anim value="Stand,Build,End"/>
            <Name value="BuildingWarpIn"/>
            <Type value="Sound"/>
            <Time value="1.266600"/>
        </Events>
        <TextureDeclares index="1" removed="1"/>
        <TextureDeclares index="2" removed="1"/>
    </CModel>
    <CModel id="CitadelOfAdunSCBWDeath" parent="BuildingDeath">
        <Model value="Assets\Buildings\Protoss\TwilightCouncilDeathEx1\TwilightCouncilDeathEx1.m3"/>
        <LowQualityModel value="ProtossBuildingDeathLow"/>
        <EditorCategories value="Race:Protoss"/>
        <Lighting value="TwilightCouncilDeath"/>
        <TextureDeclares Prefix="twilightcouncil_">
            <Adaptions TriggerOnSubstring="_Diffuse" Slot="main"/>
            <Adaptions TriggerOnSubstring="_Specular" Slot="main"/>
        </TextureDeclares>
    </CModel>
    <CModel id="CitadelOfAdunSCBWPlacement" parent="Placement" Race="Protoss">
        <Model value="Assets\Buildings\Protoss\TwilightCouncilPlacement\TwilightCouncilPlacement.m3"/>
        <LowQualityModel value="TwilightCouncil"/>
        <Lighting value="TwilightCouncil"/>
        <Radius value="-1.000000"/>
        <ScaleMax value="0.750000,0.750000,0.750000"/>
        <ScaleMin value="0.750000,0.750000,0.750000"/>
        <SelectionRadius value="0.000000"/>
        <ShadowRadius value="0.000000"/>
    </CModel>
    <CModel id="CitadelOfAdunSCBWSplat" parent="Splat">
        <Model value="Assets\Splats\Splat_TwilightCouncil\Splat_TwilightCouncil.m3"/>
        <EditorCategories value="Race:Protoss"/>
        <ScaleMax value="0.750000,0.750000,0.750000"/>
        <ScaleMin value="0.750000,0.750000,0.750000"/>
    </CModel>
    <CModel id="HighTemplarSCBWPsiStormCursorSplat" parent="UI">
        <Model value="Assets\UI\Cursors\ProtossCursor1\ProtossCursor1.m3"/>
        <EditorCategories value="Race:Protoss"/>
        <ScaleMax value="0.250000,0.250000,0.250000"/>
        <ScaleMin value="0.250000,0.250000,0.250000"/>
        <SelectionRadius value="2.500000"/>
        <ShadowRadius value="2.500000"/>
    </CModel>
    <CModel id="ReaverSCBWDeathRagdoll" parent="UnitDeathRagdoll" Race="Protoss">
        <Model value="Assets\Units\Protoss\Reaver_Ragdoll_Death\Reaver_Ragdoll_Death.m3"/>
        <Events>
            <Variation value="0"/>
            <Anim value="Death,00"/>
            <Name value="Reaver_DeathExplosion"/>
            <Type value="Sound"/>
            <Time value="1.370000"/>
            <Payload value="Reaver_DeathExplosion"/>
        </Events>
        <Lighting value="ReaverDeathRagdoll"/>
        <VariationCount value="2"/>
    </CModel>
    <CModel id="ScarabSCBWAttackImpact" parent="ImpactFX">
        <Model value="Assets\Effects\Protoss\Reaver_Missile_Impact\Reaver_Missile_Impact.m3"/>
        <EditorCategories value="Race:Protoss"/>
    </CModel>
    <CModel id="ScarabSCBW" parent="Unit" Race="Protoss">
        <Model value="Assets\Units\Test\InvisibleUnit\InvisibleUnit.m3"/>
        <Occlusion value="Show"/>
        <PlanetPanelCamera value="Star2CameraLow03"/>
        <Radius value="0.250000"/>
        <SelectionRadius value="0.294000"/>
        <ShadowRadius value="0.294000"/>
        <SquibTypeDefault value="Metal"/>
        <TechPurchaseCamera value="Star2CameraLow03"/>
        <UnitGlossaryCamera value="Star2CameraLow03"/>
    </CModel>
    <CModel id="ScarabSCBWWeapon" parent="MissileFX">
        <Model value="Assets\Effects\Protoss\Reaver_Missile\Reaver_Missile.m3"/>
    </CModel>
    <CModel id="ScoutSCBWGroundAttackImpact" parent="ImpactFX">
        <Model value="Assets\Effects\Protoss\ScoutWeaponImpact\ScoutWeaponImpact.m3"/>
        <EditorCategories value="Race:Protoss"/>
    </CModel>
    <CModel id="ScoutSCBWGroundAttackLaunch" parent="LaunchFX">
        <Model value="Assets\Effects\Protoss\ScoutWeaponLaunch\ScoutWeaponLaunch.m3"/>
        <EditorCategories value="Race:Protoss"/>
    </CModel>
    <CModel id="ScoutSCBWAirLeftAttackImpact" parent="ImpactFX">
        <Model value="Assets\Effects\Protoss\PhoenixMissileImpact\PhoenixMissileImpact.m3"/>
        <EditorCategories value="Race:Protoss"/>
    </CModel>
    <CModel id="ScoutSCBWAirRightAttackImpact" parent="ImpactFX">
        <Model value="Assets\Effects\Protoss\PhoenixMissileImpact\PhoenixMissileImpact.m3"/>
        <EditorCategories value="Race:Protoss"/>
        <Lighting value="ScoutAirLeftAttackImpact"/>
    </CModel>
    <CModel id="ScoutSCBWAirWeaponLeft" parent="MissileFX">
        <Model value="Assets\Effects\Protoss\ScoutAirMissile\ScoutAirMissile.m3"/>
        <EditorCategories value="Race:Protoss"/>
    </CModel>
    <CModel id="ScoutSCBWAirWeaponRight" parent="MissileFX">
        <Model value="Assets\Effects\Protoss\ScoutAirMissile\ScoutAirMissile.m3"/>
        <EditorCategories value="Race:Protoss"/>
    </CModel>
    <CModel id="StargateSCBW" parent="StargateBase">
        <Model value="Assets\Buildings\Protoss\StargateEx1\StargateEx1.m3"/>
        <TextureDeclares Prefix="stargate_">
            <Adaptions TriggerOnSubstring="_Diffuse" Slot="main"/>
            <Adaptions TriggerOnSubstring="_Specular" Slot="main"/>
            <Adaptions TriggerOnSubstring="_Emissive" Slot="main"/>
        </TextureDeclares>
        <TextureDeclares Prefix="tronhex1_">
            <Adaptions Slot="generic01"/>
        </TextureDeclares>
        <TextureDeclares Prefix="grad_">
            <Adaptions Slot="generic02"/>
        </TextureDeclares>
        <TextureDeclares Prefix="pulse1_">
            <Adaptions Slot="generic03"/>
        </TextureDeclares>
        <TextureDeclares Prefix="tronsquare1_">
            <Adaptions Slot="generic04"/>
        </TextureDeclares>
    </CModel>
    <CModel id="StargateSCBWBirth" parent="StargateWarpInBase">
        <Model value="Assets\Buildings\Protoss\StargateWarpIn\StargateWarpIn.m3"/>
        <TextureDeclares Prefix="stargate_">
            <Adaptions TriggerOnSubstring="_Diffuse" Slot="main"/>
            <Adaptions TriggerOnSubstring="_Specular" Slot="main"/>
            <Adaptions TriggerOnSubstring="_Emissive" Slot="main"/>
        </TextureDeclares>
    </CModel>
    <CModel id="StargateSCBWDeath" parent="StargateDeathBase">
        <Model value="Assets\Buildings\Protoss\StargateDeathEx1\StargateDeathEx1.m3"/>
        <TextureDeclares Prefix="stargate_">
            <Adaptions TriggerOnSubstring="_Diffuse" Slot="main"/>
            <Adaptions TriggerOnSubstring="_Specular" Slot="main"/>
        </TextureDeclares>
    </CModel>
    <CModel id="StargateSCBWDeathUnderConstruction" parent="BuildingDeathEx" Race="Protoss">
        <Model value="Assets\Buildings\Protoss\WarpInDeath\WarpIndeath.m3"/>
        <Lighting value="ProtossBuildingBuildDeath"/>
    </CModel>
    <CModel id="StargateSCBWPlacement" parent="StargatePlacementBase" low="StargateSCBW">
        <Model value="Assets\Buildings\Protoss\StargatePlacement\StargatePlacement.m3"/>
    </CModel>
    <CModel id="StargateSCBWPortrait" parent="ProtossBuildingPortraitBase">
        <Model value="Assets\Portraits\Protoss\ExecutorPortrait\ExecutorPortrait.m3"/>
        <Flags index="Download" value="1"/>
        <Image value="Assets\Textures\ExecutorPortrait_Static.dds"/>
        <Lighting value="ExecutorPortrait"/>
    </CModel>
    <CModel id="StargateSCBWSplat" parent="Splat">
        <Model value="Assets\Splats\Splat_Stargate\Splat_Stargate.m3"/>
        <EditorCategories value="Race:Protoss"/>
        <ScaleMax value="0.800000,0.800000,0.800000"/>
        <ScaleMin value="0.800000,0.800000,0.800000"/>
    </CModel>
</Catalog>
