<?xml version="1.0" encoding="utf-8"?>
<Catalog>
    <CTerrain id="EolianEX1">
        <BlendTextures index="0" value="MarSaraPanelsEx2"/>
        <BlendTextures index="7" value="Eolian1"/>
        <FogDensity value="0.110000"/>
        <FogStartingHeight value="2.000000"/>
        <FoliageSettingsArray index="Extreme">
            <AcceptWorldForces index="Grass" value="1"/>
            <AcceptWorldForces index="Shrubs" value="1"/>
            <AcceptWorldForces index="Trees" value="1"/>
        </FoliageSettingsArray>
    </CTerrain>
</Catalog>
